{
 "1": [
  250,
  57,
  76
 ],
 "2": [
  25,
  127,
  95
 ],
 "3": [
  165,
  163,
  163
 ],
 "4": [
  237,
  118,
  255
 ],
 "6": [
  200,
  200,
  200
 ],
 "7": [
  255,
  187,
  114
 ],
 "8": [
  191,
  218,
  227
 ],
 "9": [
  26,
  134,
  118
 ],
 "10": [
  247,
  140,
  250
 ],
 "11": [
  170,
  170,
  170
 ],
 "12": [
  240,
  170,
  251
 ],
 "14": [
  198,
  198,
  198
 ],
 "15": [
  250,
  135,
  141
 ],
 "16": [
  138,
  218,
  135
 ],
 "17": [
  255,
  155,
  254
 ],
 "18": [
  171,
  167,
  168
 ],
 "19": [
  68,
  202,
  61
 ],
 "20": [
  41,
  177,
  30
 ],
 "21": [
  201,
  196,
  197
 ],
 "22": [
  0,
  159,
  172
 ],
 "23": [
  134,
  185,
  222
 ],
 "25": [
  162,
  162,
  162
 ],
 "26": [
  254,
  129,
  255
 ],
 "27": [
  249,
  125,
  130
 ],
 "28": [
  49,
  195,
  42
 ],
 "29": [
  207,
  207,
  207
 ],
 "30": [
  250,
  112,
  75
 ],
 "31": [
  64,
  166,
  102
 ],
 "33": [
  9,
  137,
  103
 ],
 "34": [
  167,
  167,
  167
 ],
 "35": [
  218,
  132,
  246
 ],
 "36": [
  2,
  152,
  65
 ],
 "37": [
  207,
  207,
  207
 ],
 "38": [
  255,
  83,
  75
 ],
 "39": [
  66,
  164,
  98
 ],
 "41": [
  3,
  140,
  119
 ],
 "42": [
  250,
  151,
  255
 ],
 "43": [
  165,
  165,
  165
 ],
 "44": [
  89,
  179,
  99
 ],
 "45": [
  255,
  161,
  212
 ],
 "46": [
  198,
  198,
  198
 ],
 "47": [
  254,
  99,
  87
 ],
 "48": [
  65,
  157,
  82
 ],
 "49": [
  176,
  176,
  176
 ],
 "50": [
  251,
  151,
  244
 ],
 "51": [
  255,
  145,
  171
 ],
 "52": [
  46,
  179,
  40
 ],
 "53": [
  255,
  161,
  186
 ],
 "54": [
  193,
  192,
  192
 ],
 "55": [
  255,
  108,
  92
 ],
 "56": [
  132,
  190,
  254
 ],
 "57": [
  174,
  174,
  174
 ],
 "58": [
  241,
  145,
  248
 ],
 "59": [
  255,
  149,
  158
 ],
 "60": [
  34,
  180,
  57
 ],
 "61": [
  250,
  162,
  214
 ],
 "62": [
  204,
  204,
  204
 ],
 "63": [
  255,
  100,
  70
 ],
 "64": [
  255,
  142,
  164
 ],
 "65": [
  167,
  166,
  166
 ],
 "66": [
  255,
  140,
  248
 ],
 "67": [
  255,
  148,
  236
 ],
 "68": [
  33,
  142,
  55
 ],
 "69": [
  253,
  165,
  203
 ],
 "70": [
  205,
  205,
  205
 ],
 "71": [
  255,
  105,
  90
 ],
 "72": [
  254,
  63,
  56
 ],
 "73": [
  170,
  170,
  170
 ],
 "74": [
  6,
  139,
  143
 ],
 "75": [
  246,
  145,
  255
 ],
 "76": [
  254,
  165,
  218
 ],
 "77": [
  255,
  163,
  218
 ],
 "78": [
  202,
  202,
  202
 ],
 "79": [
  255,
  118,
  75
 ],
 "80": [
  255,
  65,
  94
 ],
 "81": [
  171,
  168,
  167
 ],
 "82": [
  254,
  178,
  112
 ],
 "83": [
  251,
  160,
  187
 ],
 "84": [
  52,
  162,
  64
 ],
 "85": [
  203,
  198,
  198
 ],
 "86": [
  213,
  213,
  213
 ],
 "87": [
  253,
  81,
  83
 ],
 "88": [
  251,
  117,
  65
 ],
 "89": [
  174,
  174,
  174
 ],
 "90": [
  252,
  178,
  104
 ],
 "91": [
  255,
  246,
  180
 ],
 "92": [
  68,
  184,
  33
 ],
 "93": [
  198,
  197,
  197
 ],
 "94": [
  253,
  90,
  77
 ],
 "95": [
  33,
  152,
  102
 ],
 "96": [
  254,
  172,
  210
 ],
 "97": [
  28,
  179,
  168
 ],
 "98": [
  170,
  166,
  165
 ],
 "99": [
  251,
  179,
  110
 ],
 "100": [
  251,
  182,
  247
 ],
 "101": [
  255,
  157,
  207
 ],
 "102": [
  204,
  204,
  204
 ],
 "103": [
  255,
  118,
  74
 ],
 "104": [
  39,
  152,
  100
 ],
 "105": [
  252,
  153,
  112
 ],
 "106": [
  254,
  187,
  212
 ],
 "107": [
  28,
  148,
  87
 ],
 "108": [
  176,
  173,
  173
 ],
 "109": [
  196,
  191,
  189
 ],
 "110": [
  255,
  86,
  89
 ],
 "111": [
  28,
  150,
  100
 ],
 "112": [
  255,
  154,
  181
 ],
 "113": [
  24,
  128,
  107
 ],
 "114": [
  255,
  198,
  109
 ],
 "115": [
  255,
  149,
  251
 ],
 "116": [
  177,
  177,
  177
 ],
 "117": [
  200,
  195,
  196
 ],
 "118": [
  253,
  117,
  79
 ],
 "119": [
  31,
  146,
  120
 ],
 "120": [
  31,
  152,
  125
 ],
 "121": [
  15,
  140,
  128
 ],
 "122": [
  255,
  164,
  105
 ],
 "123": [
  255,
  194,
  114
 ],
 "124": [
  173,
  173,
  173
 ],
 "125": [
  208,
  202,
  203
 ],
 "126": [
  246,
  94,
  74
 ],
 "127": [
  255,
  147,
  169
 ],
 "128": [
  245,
  136,
  246
 ],
 "129": [
  165,
  165,
  165
 ],
 "130": [
  255,
  186,
  141
 ],
 "131": [
  144,
  235,
  141
 ],
 "132": [
  45,
  170,
  49
 ],
 "133": [
  255,
  82,
  73
 ],
 "134": [
  201,
  195,
  194
 ],
 "135": [
  251,
  174,
  215
 ],
 "136": [
  253,
  177,
  209
 ],
 "137": [
  246,
  175,
  143
 ],
 "138": [
  249,
  156,
  157
 ],
 "139": [
  43,
  187,
  50
 ],
 "140": [
  174,
  174,
  174
 ],
 "141": [
  255,
  85,
  71
 ],
 "142": [
  210,
  204,
  205
 ],
 "143": [
  255,
  184,
  209
 ],
 "144": [
  118,
  185,
  250
 ],
 "145": [
  166,
  166,
  166
 ],
 "146": [
  251,
  179,
  132
 ],
 "147": [
  250,
  191,
  151
 ],
 "148": [
  1,
  162,
  111
 ],
 "149": [
  255,
  148,
  145
 ],
 "150": [
  196,
  193,
  193
 ],
 "151": [
  157,
  240,
  210
 ],
 "152": [
  102,
  208,
  168
 ],
 "153": [
  176,
  174,
  174
 ],
 "154": [
  253,
  170,
  228
 ],
 "155": [
  250,
  144,
  157
 ],
 "156": [
  5,
  149,
  144
 ],
 "157": [
  255,
  93,
  80
 ],
 "158": [
  200,
  200,
  200
 ],
 "159": [
  84,
  191,
  148
 ],
 "160": [
  83,
  190,
  170
 ],
 "161": [
  252,
  163,
  199
 ],
 "162": [
  255,
  184,
  141
 ],
 "163": [
  33,
  150,
  87
 ],
 "164": [
  168,
  160,
  160
 ],
 "165": [
  246,
  161,
  253
 ],
 "166": [
  209,
  188,
  187
 ],
 "167": [
  82,
  196,
  146
 ],
 "168": [
  83,
  185,
  151
 ],
 "169": [
  255,
  182,
  209
 ],
 "170": [
  255,
  137,
  132
 ],
 "171": [
  46,
  162,
  78
 ],
 "173": [
  250,
  89,
  64
 ],
 "174": [
  199,
  192,
  189
 ],
 "175": [
  81,
  192,
  127
 ],
 "177": [
  255,
  180,
  204
 ],
 "178": [
  250,
  139,
  151
 ],
 "179": [
  64,
  163,
  80
 ],
 "180": [
  0,
  146,
  117
 ],
 "181": [
  255,
  138,
  171
 ],
 "182": [
  202,
  202,
  202
 ],
 "183": [
  95,
  196,
  156
 ],
 "184": [
  38,
  143,
  69
 ],
 "185": [
  255,
  174,
  224
 ],
 "186": [
  255,
  159,
  165
 ],
 "187": [
  6,
  150,
  103
 ],
 "188": [
  157,
  240,
  210
 ],
 "189": [
  255,
  161,
  145
 ],
 "190": [
  198,
  196,
  196
 ],
 "191": [
  88,
  182,
  138
 ],
 "192": [
  91,
  234,
  174
 ],
 "193": [
  254,
  188,
  226
 ],
 "194": [
  236,
  60,
  98
 ],
 "195": [
  39,
  169,
  88
 ],
 "196": [
  149,
  228,
  200
 ],
 "197": [
  255,
  155,
  247
 ],
 "198": [
  205,
  205,
  205
 ],
 "199": [
  85,
  186,
  144
 ],
 "200": [
  100,
  234,
  211
 ],
 "201": [
  27,
  127,
  92
 ],
 "202": [
  244,
  187,
  212
 ],
 "203": [
  248,
  160,
  207
 ],
 "204": [
  157,
  240,
  210
 ],
 "205": [
  207,
  203,
  203
 ],
 "206": [
  255,
  199,
  230
 ],
 "207": [
  254,
  181,
  214
 ],
 "208": [
  96,
  221,
  170
 ],
 "209": [
  251,
  171,
  217
 ],
 "210": [
  255,
  79,
  58
 ],
 "211": [
  70,
  166,
  108
 ],
 "212": [
  130,
  199,
  174
 ],
 "213": [
  207,
  207,
  207
 ],
 "214": [
  246,
  123,
  229
 ],
 "215": [
  249,
  149,
  255
 ],
 "216": [
  83,
  231,
  168
 ],
 "217": [
  255,
  197,
  226
 ],
 "218": [
  255,
  131,
  152
 ],
 "219": [
  35,
  151,
  93
 ],
 "220": [
  130,
  199,
  174
 ],
 "221": [
  205,
  194,
  195
 ],
 "222": [
  255,
  195,
  221
 ],
 "223": [
  255,
  123,
  74
 ],
 "224": [
  115,
  240,
  193
 ],
 "225": [
  243,
  166,
  201
 ],
 "226": [
  245,
  78,
  89
 ],
 "227": [
  58,
  162,
  108
 ],
 "228": [
  154,
  210,
  189
 ],
 "229": [
  210,
  210,
  210
 ],
 "230": [
  253,
  184,
  231
 ],
 "231": [
  254,
  139,
  255
 ],
 "232": [
  95,
  229,
  202
 ],
 "233": [
  6,
  135,
  129
 ],
 "234": [
  20,
  180,
  142
 ],
 "235": [
  253,
  184,
  238
 ],
 "236": [
  130,
  199,
  174
 ],
 "237": [
  209,
  204,
  205
 ],
 "238": [
  255,
  183,
  152
 ],
 "239": [
  250,
  145,
  162
 ],
 "240": [
  92,
  232,
  195
 ],
 "241": [
  1,
  141,
  172
 ],
 "242": [
  144,
  215,
  240
 ],
 "243": [
  0,
  151,
  157
 ],
 "244": [
  154,
  210,
  189
 ],
 "245": [
  196,
  187,
  187
 ],
 "246": [
  235,
  142,
  255
 ],
 "247": [
  1,
  147,
  153
 ],
 "248": [
  85,
  230,
  153
 ],
 "249": [
  0,
  121,
  145
 ],
 "250": [
  138,
  213,
  234
 ],
 "251": [
  5,
  148,
  156
 ],
 "252": [
  1,
  135,
  148
 ],
 "253": [
  200,
  200,
  200
 ],
 "254": [
  26,
  166,
  152
 ],
 "255": [
  255,
  135,
  149
 ],
 "256": [
  92,
  230,
  202
 ],
 "257": [
  8,
  125,
  142
 ],
 "258": [
  144,
  223,
  229
 ],
 "259": [
  54,
  184,
  31
 ],
 "260": [
  162,
  229,
  196
 ],
 "261": [
  204,
  201,
  201
 ],
 "262": [
  253,
  138,
  147
 ],
 "263": [
  254,
  101,
  63
 ],
 "264": [
  36,
  129,
  71
 ],
 "266": [
  155,
  218,
  241
 ],
 "267": [
  162,
  218,
  155
 ],
 "268": [
  150,
  218,
  188
 ],
 "269": [
  6,
  119,
  142
 ],
 "270": [
  205,
  202,
  202
 ],
 "271": [
  231,
  110,
  249
 ],
 "272": [
  250,
  99,
  74
 ],
 "274": [
  28,
  168,
  166
 ],
 "275": [
  144,
  203,
  237
 ],
 "276": [
  110,
  205,
  187
 ],
 "277": [
  209,
  208,
  208
 ],
 "278": [
  128,
  192,
  226
 ],
 "279": [
  25,
  160,
  162
 ],
 "280": [
  255,
  199,
  137
 ],
 "281": [
  7,
  135,
  110
 ],
 "283": [
  255,
  159,
  120
 ],
 "284": [
  104,
  206,
  168
 ],
 "285": [
  199,
  188,
  188
 ],
 "286": [
  254,
  77,
  103
 ],
 "287": [
  180,
  196,
  230
 ],
 "288": [
  32,
  141,
  101
 ],
 "289": [
  18,
  186,
  180
 ],
 "290": [
  242,
  72,
  59
 ],
 "291": [
  111,
  202,
  169
 ],
 "292": [
  123,
  189,
  223
 ],
 "293": [
  200,
  200,
  200
 ],
 "294": [
  255,
  148,
  227
 ],
 "295": [
  157,
  231,
  156
 ],
 "296": [
  54,
  160,
  92
 ],
 "297": [
  95,
  209,
  174
 ],
 "298": [
  174,
  186,
  223
 ],
 "299": [
  25,
  156,
  103
 ],
 "300": [
  255,
  141,
  138
 ],
 "301": [
  201,
  201,
  201
 ],
 "302": [
  252,
  123,
  227
 ],
 "303": [
  177,
  231,
  164
 ],
 "304": [
  45,
  173,
  105
 ],
 "305": [
  8,
  121,
  144
 ],
 "306": [
  101,
  203,
  178
 ],
 "307": [
  255,
  188,
  209
 ],
 "308": [
  1,
  173,
  165
 ],
 "309": [
  210,
  210,
  209
 ],
 "310": [
  150,
  234,
  241
 ],
 "311": [
  175,
  233,
  160
 ],
 "312": [
  53,
  184,
  31
 ],
 "313": [
  255,
  100,
  255
 ],
 "314": [
  35,
  158,
  100
 ],
 "315": [
  112,
  255,
  113
 ],
 "316": [
  250,
  140,
  165
 ],
 "317": [
  210,
  210,
  210
 ],
 "318": [
  255,
  177,
  134
 ],
 "319": [
  132,
  234,
  129
 ],
 "320": [
  36,
  158,
  100
 ],
 "321": [
  250,
  143,
  155
 ],
 "322": [
  19,
  125,
  107
 ],
 "323": [
  255,
  144,
  255
 ],
 "324": [
  50,
  178,
  43
 ],
 "325": [
  249,
  140,
  180
 ],
 "326": [
  208,
  204,
  203
 ],
 "327": [
  127,
  235,
  123
 ],
 "328": [
  34,
  157,
  139
 ],
 "329": [
  20,
  130,
  103
 ],
 "330": [
  16,
  163,
  126
 ],
 "331": [
  253,
  89,
  55
 ],
 "332": [
  255,
  90,
  86
 ],
 "333": [
  145,
  224,
  242
 ],
 "334": [
  125,
  235,
  138
 ],
 "335": [
  0,
  0,
  0
 ],
 "336": [
  198,
  190,
  190
 ],
 "337": [
  22,
  128,
  99
 ],
 "338": [
  255,
  70,
  69
 ],
 "339": [
  255,
  122,
  255
 ],
 "340": [
  0,
  128,
  172
 ],
 "341": [
  202,
  202,
  202
 ],
 "342": [
  160,
  171,
  214
 ],
 "343": [
  255,
  112,
  128
 ],
 "344": [
  33,
  155,
  129
 ],
 "345": [
  18,
  130,
  118
 ],
 "346": [
  27,
  128,
  109
 ],
 "347": [
  255,
  67,
  69
 ],
 "348": [
  255,
  144,
  255
 ],
 "349": [
  202,
  199,
  200
 ],
 "350": [
  255,
  187,
  148
 ],
 "351": [
  176,
  186,
  226
 ],
 "352": [
  33,
  141,
  74
 ],
 "353": [
  24,
  131,
  101
 ],
 "354": [
  255,
  155,
  205
 ],
 "355": [
  32,
  157,
  98
 ],
 "356": [
  244,
  102,
  47
 ],
 "357": [
  198,
  190,
  193
 ],
 "358": [
  255,
  181,
  146
 ],
 "359": [
  180,
  187,
  219
 ],
 "360": [
  174,
  214,
  173
 ],
 "361": [
  21,
  129,
  97
 ],
 "362": [
  255,
  147,
  164
 ],
 "363": [
  50,
  165,
  94
 ],
 "364": [
  237,
  119,
  62
 ],
 "365": [
  199,
  199,
  199
 ],
 "366": [
  255,
  128,
  169
 ],
 "367": [
  167,
  178,
  212
 ],
 "368": [
  0,
  0,
  0
 ],
 "369": [
  22,
  133,
  122
 ],
 "370": [
  255,
  179,
  217
 ],
 "371": [
  45,
  185,
  40
 ],
 "372": [
  246,
  171,
  219
 ],
 "373": [
  209,
  209,
  209
 ],
 "374": [
  253,
  153,
  244
 ],
 "375": [
  138,
  208,
  73
 ],
 "376": [
  85,
  228,
  184
 ],
 "377": [
  0,
  92,
  128
 ],
 "378": [
  22,
  117,
  84
 ],
 "379": [
  255,
  198,
  226
 ],
 "380": [
  203,
  203,
  203
 ],
 "381": [
  252,
  137,
  255
 ],
 "382": [
  119,
  206,
  67
 ],
 "383": [
  99,
  233,
  212
 ],
 "384": [
  200,
  197,
  197
 ],
 "385": [
  7,
  138,
  114
 ],
 "386": [
  255,
  165,
  210
 ],
 "387": [
  78,
  173,
  41
 ],
 "388": [
  203,
  203,
  203
 ],
 "389": [
  200,
  199,
  199
 ],
 "390": [
  248,
  80,
  84
 ],
 "391": [
  126,
  208,
  75
 ],
 "392": [
  146,
  221,
  178
 ],
 "393": [
  12,
  119,
  136
 ],
 "394": [
  8,
  136,
  141
 ],
 "395": [
  240,
  174,
  210
 ],
 "396": [
  197,
  191,
  191
 ],
 "397": [
  193,
  187,
  187
 ],
 "398": [
  255,
  156,
  120
 ],
 "399": [
  126,
  208,
  75
 ],
 "400": [
  95,
  214,
  175
 ],
 "401": [
  6,
  129,
  140
 ],
 "402": [
  7,
  111,
  141
 ],
 "403": [
  129,
  180,
  225
 ],
 "404": [
  198,
  189,
  190
 ],
 "405": [
  208,
  208,
  208
 ],
 "406": [
  255,
  131,
  141
 ],
 "407": [
  102,
  168,
  61
 ],
 "408": [
  72,
  215,
  138
 ],
 "409": [
  10,
  138,
  139
 ],
 "410": [
  204,
  204,
  204
 ],
 "411": [
  135,
  161,
  228
 ],
 "412": [
  37,
  137,
  100
 ],
 "413": [
  192,
  179,
  181
 ],
 "414": [
  250,
  126,
  138
 ],
 "415": [
  126,
  208,
  75
 ],
 "416": [
  90,
  225,
  200
 ],
 "417": [
  5,
  168,
  168
 ],
 "418": [
  121,
  221,
  226
 ],
 "419": [
  67,
  190,
  38
 ],
 "420": [
  201,
  193,
  193
 ],
 "421": [
  6,
  143,
  138
 ],
 "422": [
  253,
  136,
  133
 ],
 "423": [
  135,
  211,
  80
 ],
 "424": [
  102,
  221,
  208
 ],
 "425": [
  9,
  134,
  142
 ],
 "426": [
  126,
  204,
  222
 ],
 "427": [
  13,
  158,
  152
 ],
 "428": [
  203,
  203,
  203
 ],
 "429": [
  255,
  182,
  225
 ],
 "430": [
  29,
  171,
  148
 ],
 "431": [
  126,
  208,
  75
 ],
 "432": [
  247,
  87,
  79
 ],
 "433": [
  5,
  135,
  119
 ],
 "434": [
  31,
  177,
  171
 ],
 "435": [
  126,
  192,
  232
 ],
 "436": [
  200,
  200,
  200
 ],
 "437": [
  252,
  150,
  195
 ],
 "438": [
  126,
  208,
  75
 ],
 "439": [
  248,
  80,
  48
 ],
 "440": [
  37,
  136,
  109
 ],
 "441": [
  3,
  132,
  142
 ],
 "442": [
  29,
  165,
  127
 ],
 "443": [
  207,
  207,
  207
 ],
 "444": [
  255,
  162,
  156
 ],
 "445": [
  251,
  165,
  189
 ],
 "446": [
  102,
  168,
  61
 ],
 "447": [
  255,
  133,
  63
 ],
 "448": [
  40,
  148,
  107
 ],
 "449": [
  209,
  207,
  206
 ],
 "450": [
  26,
  124,
  85
 ],
 "451": [
  157,
  226,
  152
 ],
 "452": [
  255,
  132,
  64
 ],
 "453": [
  24,
  128,
  100
 ],
 "454": [
  126,
  208,
  75
 ],
 "455": [
  255,
  75,
  48
 ],
 "456": [
  0,
  137,
  148
 ],
 "457": [
  1,
  135,
  109
 ],
 "458": [
  136,
  230,
  252
 ],
 "459": [
  210,
  210,
  210
 ],
 "460": [
  254,
  124,
  241
 ],
 "461": [
  17,
  129,
  103
 ],
 "462": [
  244,
  162,
  126
 ],
 "463": [
  113,
  207,
  78
 ],
 "464": [
  255,
  80,
  65
 ],
 "465": [
  120,
  204,
  242
 ],
 "466": [
  208,
  208,
  208
 ],
 "467": [
  255,
  76,
  62
 ],
 "468": [
  51,
  186,
  29
 ],
 "469": [
  9,
  110,
  140
 ],
 "470": [
  245,
  74,
  53
 ],
 "471": [
  126,
  208,
  75
 ],
 "472": [
  119,
  178,
  221
 ],
 "473": [
  124,
  173,
  246
 ],
 "474": [
  205,
  205,
  205
 ],
 "475": [
  255,
  138,
  142
 ],
 "476": [
  34,
  136,
  79
 ],
 "477": [
  152,
  214,
  249
 ],
 "478": [
  28,
  128,
  108
 ],
 "479": [
  126,
  208,
  75
 ],
 "480": [
  116,
  184,
  223
 ],
 "481": [
  121,
  217,
  253
 ],
 "482": [
  202,
  202,
  202
 ],
 "483": [
  247,
  132,
  189
 ],
 "484": [
  34,
  132,
  99
 ],
 "485": [
  152,
  214,
  249
 ],
 "486": [
  126,
  208,
  75
 ],
 "487": [
  126,
  208,
  219
 ],
 "488": [
  37,
  126,
  86
 ],
 "489": [
  125,
  201,
  248
 ],
 "490": [
  209,
  208,
  208
 ],
 "491": [
  253,
  69,
  57
 ],
 "492": [
  36,
  141,
  106
 ],
 "493": [
  128,
  205,
  248
 ],
 "494": [
  254,
  148,
  241
 ],
 "495": [
  102,
  168,
  61
 ],
 "496": [
  169,
  213,
  162
 ],
 "497": [
  5,
  95,
  133
 ],
 "498": [
  189,
  201,
  224
 ],
 "499": [
  201,
  190,
  187
 ],
 "500": [
  31,
  157,
  90
 ],
 "501": [
  10,
  127,
  138
 ],
 "502": [
  79,
  194,
  68
 ],
 "503": [
  252,
  141,
  255
 ],
 "504": [
  126,
  208,
  75
 ],
 "505": [
  169,
  180,
  222
 ],
 "506": [
  204,
  204,
  204
 ],
 "507": [
  154,
  210,
  189
 ],
 "508": [
  45,
  180,
  37
 ],
 "509": [
  74,
  195,
  64
 ],
 "510": [
  16,
  123,
  96
 ],
 "511": [
  240,
  156,
  255
 ],
 "512": [
  240,
  240,
  128
 ],
 "513": [
  189,
  194,
  224
 ],
 "514": [
  200,
  200,
  200
 ],
 "515": [
  255,
  106,
  54
 ],
 "516": [
  30,
  131,
  85
 ],
 "517": [
  169,
  240,
  222
 ],
 "518": [
  102,
  199,
  74
 ],
 "519": [
  228,
  240,
  126
 ],
 "520": [
  2,
  124,
  149
 ],
 "521": [
  178,
  189,
  223
 ],
 "522": [
  201,
  197,
  196
 ],
 "523": [
  255,
  79,
  72
 ],
 "524": [
  31,
  139,
  78
 ],
 "525": [
  255,
  89,
  53
 ],
 "526": [
  60,
  187,
  45
 ],
 "527": [
  5,
  158,
  133
 ],
 "528": [
  237,
  244,
  125
 ],
 "529": [
  176,
  186,
  219
 ],
 "530": [
  202,
  202,
  202
 ],
 "531": [
  255,
  147,
  243
 ],
 "532": [
  0,
  120,
  166
 ],
 "533": [
  3,
  136,
  121
 ],
 "534": [
  254,
  191,
  136
 ],
 "535": [
  151,
  212,
  152
 ],
 "536": [
  130,
  175,
  216
 ],
 "537": [
  181,
  189,
  227
 ],
 "538": [
  199,
  199,
  199
 ],
 "539": [
  247,
  141,
  231
 ],
 "540": [
  10,
  10,
  10
 ],
 "541": [
  21,
  176,
  179
 ],
 "542": [
  28,
  161,
  147
 ],
 "543": [
  55,
  190,
  38
 ],
 "544": [
  131,
  184,
  226
 ],
 "545": [
  31,
  165,
  151
 ],
 "546": [
  184,
  205,
  222
 ],
 "547": [
  200,
  200,
  200
 ],
 "548": [
  255,
  140,
  233
 ],
 "549": [
  255,
  112,
  128
 ],
 "550": [
  36,
  188,
  32
 ],
 "551": [
  124,
  195,
  220
 ],
 "552": [
  251,
  181,
  129
 ],
 "553": [
  208,
  208,
  208
 ],
 "554": [
  179,
  188,
  228
 ],
 "555": [
  255,
  140,
  244
 ],
 "556": [
  86,
  174,
  98
 ],
 "557": [
  251,
  54,
  92
 ],
 "558": [
  18,
  133,
  113
 ],
 "559": [
  124,
  225,
  233
 ],
 "560": [
  255,
  165,
  224
 ],
 "561": [
  0,
  138,
  145
 ],
 "562": [
  184,
  192,
  223
 ],
 "563": [
  209,
  202,
  203
 ],
 "564": [
  141,
  169,
  209
 ],
 "565": [
  5,
  133,
  138
 ],
 "566": [
  168,
  236,
  211
 ],
 "567": [
  176,
  240,
  255
 ],
 "568": [
  251,
  172,
  217
 ],
 "569": [
  178,
  197,
  221
 ],
 "570": [
  198,
  195,
  196
 ],
 "571": [
  255,
  124,
  137
 ],
 "572": [
  61,
  166,
  78
 ],
 "573": [
  7,
  135,
  146
 ],
 "574": [
  255,
  159,
  133
 ],
 "575": [
  255,
  148,
  143
 ],
 "576": [
  255,
  187,
  214
 ],
 "577": [
  23,
  121,
  78
 ],
 "578": [
  189,
  200,
  228
 ],
 "579": [
  201,
  201,
  201
 ],
 "580": [
  255,
  129,
  223
 ],
 "581": [
  141,
  180,
  206
 ],
 "582": [
  38,
  135,
  96
 ],
 "583": [
  138,
  218,
  135
 ],
 "584": [
  98,
  233,
  202
 ],
 "585": [
  176,
  195,
  227
 ],
 "586": [
  200,
  200,
  200
 ],
 "587": [
  252,
  141,
  238
 ],
 "588": [
  73,
  167,
  130
 ],
 "589": [
  98,
  208,
  159
 ],
 "590": [
  26,
  167,
  98
 ],
 "591": [
  255,
  158,
  250
 ],
 "592": [
  92,
  223,
  166
 ],
 "593": [
  0,
  139,
  121
 ],
 "594": [
  176,
  191,
  228
 ],
 "595": [
  206,
  192,
  191
 ],
 "596": [
  148,
  157,
  218
 ],
 "597": [
  98,
  208,
  163
 ],
 "598": [
  2,
  148,
  110
 ],
 "599": [
  255,
  145,
  152
 ],
 "600": [
  0,
  147,
  150
 ],
 "601": [
  2,
  109,
  135
 ],
 "602": [
  177,
  189,
  222
 ],
 "603": [
  200,
  198,
  199
 ],
 "604": [
  252,
  215,
  152
 ],
 "605": [
  100,
  207,
  183
 ],
 "606": [
  13,
  162,
  158
 ],
 "607": [
  255,
  155,
  212
 ],
 "608": [
  39,
  138,
  96
 ],
 "609": [
  255,
  147,
  131
 ],
 "610": [
  29,
  165,
  175
 ],
 "611": [
  205,
  205,
  205
 ],
 "612": [
  253,
  163,
  110
 ],
 "613": [
  3,
  126,
  141
 ],
 "614": [
  246,
  64,
  60
 ],
 "615": [
  234,
  139,
  255
 ],
 "616": [
  252,
  153,
  231
 ],
 "617": [
  255,
  152,
  144
 ],
 "618": [
  193,
  192,
  192
 ],
 "619": [
  149,
  228,
  200
 ],
 "620": [
  34,
  133,
  90
 ],
 "621": [
  239,
  179,
  130
 ],
 "622": [
  24,
  164,
  148
 ],
 "623": [
  152,
  214,
  249
 ],
 "624": [
  169,
  167,
  166
 ],
 "625": [
  22,
  126,
  98
 ],
 "626": [
  251,
  143,
  140
 ],
 "627": [
  199,
  199,
  199
 ],
 "628": [
  255,
  140,
  253
 ],
 "629": [
  255,
  173,
  158
 ],
 "630": [
  40,
  143,
  110
 ],
 "631": [
  97,
  231,
  183
 ],
 "632": [
  102,
  168,
  61
 ],
 "633": [
  210,
  210,
  210
 ],
 "634": [
  253,
  148,
  249
 ],
 "635": [
  0,
  158,
  178
 ],
 "636": [
  255,
  152,
  147
 ],
 "637": [
  251,
  125,
  122
 ],
 "638": [
  6,
  145,
  92
 ],
 "639": [
  81,
  220,
  224
 ],
 "640": [
  243,
  159,
  213
 ],
 "641": [
  202,
  196,
  196
 ],
 "642": [
  255,
  166,
  194
 ],
 "643": [
  5,
  149,
  109
 ],
 "644": [
  32,
  155,
  117
 ],
 "645": [
  255,
  252,
  145
 ],
 "646": [
  172,
  219,
  163
 ],
 "647": [
  94,
  233,
  165
 ],
 "648": [
  37,
  161,
  80
 ],
 "649": [
  3,
  134,
  120
 ],
 "650": [
  206,
  206,
  206
 ],
 "651": [
  246,
  164,
  213
 ],
 "652": [
  253,
  82,
  85
 ],
 "653": [
  255,
  171,
  200
 ],
 "654": [
  24,
  130,
  110
 ],
 "655": [
  105,
  237,
  195
 ],
 "656": [
  28,
  148,
  82
 ],
 "657": [
  23,
  128,
  89
 ],
 "658": [
  204,
  204,
  204
 ],
 "659": [
  252,
  161,
  221
 ],
 "660": [
  251,
  88,
  134
 ],
 "661": [
  253,
  173,
  217
 ],
 "662": [
  2,
  148,
  149
 ],
 "663": [
  95,
  235,
  229
 ],
 "664": [
  77,
  178,
  37
 ],
 "665": [
  201,
  201,
  201
 ],
 "666": [
  255,
  168,
  210
 ],
 "667": [
  36,
  144,
  89
 ],
 "668": [
  254,
  102,
  78
 ],
 "669": [
  8,
  133,
  140
 ],
 "670": [
  16,
  126,
  80
 ],
 "671": [
  24,
  164,
  160
 ],
 "672": [
  147,
  229,
  249
 ],
 "673": [
  198,
  198,
  198
 ],
 "674": [
  252,
  169,
  213
 ],
 "675": [
  34,
  159,
  103
 ],
 "676": [
  255,
  72,
  102
 ],
 "677": [
  17,
  173,
  131
 ],
 "678": [
  3,
  142,
  131
 ],
 "679": [
  255,
  183,
  156
 ],
 "680": [
  33,
  142,
  94
 ],
 "681": [
  200,
  191,
  190
 ],
 "682": [
  248,
  152,
  183
 ],
 "683": [
  6,
  161,
  175
 ],
 "684": [
  243,
  101,
  67
 ],
 "685": [
  253,
  135,
  136
 ],
 "686": [
  24,
  121,
  78
 ],
 "687": [
  24,
  161,
  167
 ],
 "688": [
  176,
  255,
  184
 ],
 "689": [
  245,
  70,
  71
 ],
 "690": [
  200,
  200,
  200
 ],
 "691": [
  255,
  165,
  221
 ],
 "692": [
  3,
  3,
  3
 ],
 "693": [
  252,
  79,
  58
 ],
 "694": [
  37,
  155,
  102
 ],
 "695": [
  112,
  255,
  112
 ],
 "696": [
  1,
  112,
  143
 ],
 "697": [
  203,
  196,
  195
 ],
 "698": [
  154,
  210,
  189
 ],
 "699": [
  33,
  151,
  119
 ],
 "700": [
  255,
  70,
  56
 ],
 "701": [
  247,
  185,
  210
 ],
 "702": [
  23,
  129,
  92
 ],
 "703": [
  138,
  218,
  135
 ],
 "704": [
  29,
  146,
  119
 ],
 "705": [
  205,
  203,
  203
 ],
 "706": [
  226,
  142,
  255
 ],
 "707": [
  87,
  177,
  97
 ],
 "708": [
  255,
  92,
  76
 ],
 "709": [
  247,
  121,
  118
 ],
 "710": [
  199,
  198,
  198
 ],
 "711": [
  247,
  161,
  232
 ],
 "712": [
  54,
  176,
  38
 ],
 "713": [
  200,
  198,
  197
 ],
 "714": [
  36,
  138,
  94
 ],
 "715": [
  71,
  183,
  33
 ],
 "716": [
  252,
  74,
  58
 ],
 "717": [
  212,
  205,
  206
 ],
 "718": [
  255,
  123,
  125
 ],
 "719": [
  26,
  123,
  125
 ],
 "720": [
  247,
  164,
  198
 ],
 "721": [
  10,
  112,
  142
 ],
 "722": [
  200,
  200,
  200
 ],
 "723": [
  39,
  134,
  77
 ],
 "724": [
  254,
  88,
  56
 ],
 "725": [
  255,
  149,
  129
 ],
 "726": [
  175,
  214,
  76
 ],
 "727": [
  56,
  190,
  32
 ],
 "728": [
  205,
  205,
  205
 ],
 "729": [
  20,
  119,
  178
 ],
 "730": [
  205,
  196,
  197
 ],
 "731": [
  39,
  140,
  92
 ],
 "732": [
  253,
  72,
  63
 ],
 "733": [
  251,
  118,
  142
 ],
 "734": [
  126,
  208,
  75
 ],
 "735": [
  0,
  130,
  147
 ],
 "736": [
  204,
  200,
  200
 ],
 "737": [
  201,
  201,
  201
 ],
 "738": [
  37,
  134,
  93
 ],
 "739": [
  55,
  163,
  90
 ],
 "740": [
  241,
  108,
  63
 ],
 "741": [
  255,
  144,
  135
 ],
 "742": [
  128,
  210,
  74
 ],
 "743": [
  36,
  185,
  33
 ],
 "744": [
  209,
  207,
  206
 ],
 "745": [
  203,
  192,
  191
 ],
 "746": [
  36,
  142,
  95
 ],
 "747": [
  83,
  179,
  94
 ],
 "748": [
  255,
  125,
  62
 ],
 "749": [
  255,
  160,
  240
 ],
 "750": [
  11,
  141,
  138
 ],
 "751": [
  117,
  210,
  77
 ],
 "752": [
  203,
  203,
  203
 ],
 "753": [
  207,
  207,
  207
 ],
 "754": [
  123,
  217,
  245
 ],
 "755": [
  9,
  146,
  150
 ],
 "756": [
  255,
  59,
  79
 ],
 "757": [
  253,
  148,
  255
 ],
 "758": [
  139,
  202,
  76
 ],
 "759": [
  0,
  158,
  147
 ],
 "760": [
  211,
  203,
  202
 ],
 "761": [
  255,
  87,
  73
 ],
 "762": [
  194,
  194,
  194
 ],
 "763": [
  249,
  114,
  82
 ],
 "764": [
  58,
  180,
  33
 ],
 "765": [
  248,
  175,
  189
 ],
 "766": [
  126,
  208,
  75
 ],
 "767": [
  39,
  158,
  89
 ],
 "768": [
  199,
  199,
  199
 ],
 "769": [
  255,
  73,
  78
 ],
 "770": [
  210,
  205,
  206
 ],
 "771": [
  255,
  155,
  136
 ],
 "772": [
  65,
  162,
  94
 ],
 "773": [
  246,
  171,
  213
 ],
 "774": [
  22,
  159,
  150
 ],
 "775": [
  96,
  199,
  66
 ],
 "776": [
  211,
  209,
  209
 ],
 "777": [
  253,
  94,
  74
 ],
 "778": [
  2,
  135,
  150
 ],
 "779": [
  196,
  196,
  196
 ],
 "780": [
  151,
  236,
  147
 ],
 "781": [
  248,
  172,
  196
 ],
 "782": [
  106,
  209,
  71
 ],
 "783": [
  37,
  152,
  93
 ],
 "784": [
  202,
  202,
  202
 ],
 "785": [
  255,
  99,
  65
 ],
 "786": [
  18,
  173,
  161
 ],
 "787": [
  211,
  211,
  211
 ],
 "788": [
  89,
  218,
  171
 ],
 "789": [
  255,
  176,
  196
 ],
 "790": [
  123,
  195,
  72
 ],
 "791": [
  0,
  126,
  152
 ],
 "792": [
  207,
  198,
  199
 ],
 "793": [
  23,
  124,
  125
 ],
 "794": [
  201,
  196,
  197
 ],
 "795": [
  237,
  145,
  248
 ],
 "796": [
  239,
  91,
  60
 ],
 "797": [
  231,
  87,
  56
 ],
 "798": [
  210,
  202,
  204
 ],
 "799": [
  126,
  208,
  75
 ],
 "800": [
  39,
  153,
  127
 ],
 "801": [
  8,
  149,
  131
 ],
 "802": [
  207,
  207,
  207
 ],
 "803": [
  133,
  153,
  204
 ],
 "804": [
  243,
  50,
  52
 ],
 "805": [
  0,
  113,
  130
 ],
 "806": [
  24,
  126,
  90
 ],
 "807": [
  105,
  206,
  71
 ],
 "808": [
  197,
  191,
  191
 ],
 "809": [
  179,
  192,
  223
 ],
 "810": [
  65,
  164,
  101
 ],
 "811": [
  250,
  121,
  223
 ],
 "812": [
  197,
  196,
  196
 ],
 "813": [
  207,
  206,
  206
 ],
 "814": [
  164,
  218,
  164
 ],
 "815": [
  135,
  218,
  77
 ],
 "816": [
  5,
  159,
  160
 ],
 "817": [
  202,
  202,
  202
 ],
 "818": [
  133,
  153,
  204
 ],
 "819": [
  64,
  165,
  119
 ],
 "820": [
  250,
  121,
  255
 ],
 "821": [
  3,
  143,
  104
 ],
 "822": [
  50,
  184,
  37
 ],
 "823": [
  150,
  216,
  65
 ],
 "824": [
  208,
  207,
  207
 ],
 "825": [
  204,
  204,
  204
 ],
 "826": [
  150,
  167,
  211
 ],
 "827": [
  80,
  165,
  82
 ],
 "828": [
  252,
  115,
  225
 ],
 "829": [
  79,
  194,
  68
 ],
 "830": [
  253,
  88,
  69
 ],
 "831": [
  26,
  153,
  127
 ],
 "832": [
  202,
  202,
  202
 ],
 "833": [
  198,
  198,
  198
 ],
 "834": [
  248,
  122,
  251
 ],
 "835": [
  162,
  177,
  216
 ],
 "836": [
  15,
  159,
  148
 ],
 "837": [
  79,
  194,
  68
 ],
 "838": [
  25,
  127,
  101
 ],
 "839": [
  247,
  168,
  206
 ],
 "840": [
  203,
  203,
  203
 ],
 "841": [
  211,
  207,
  208
 ],
 "842": [
  250,
  117,
  217
 ],
 "843": [
  114,
  213,
  105
 ],
 "844": [
  27,
  152,
  93
 ],
 "845": [
  75,
  181,
  71
 ],
 "846": [
  233,
  246,
  190
 ],
 "847": [
  0,
  150,
  139
 ],
 "848": [
  201,
  201,
  201
 ],
 "849": [
  21,
  164,
  99
 ],
 "850": [
  202,
  202,
  202
 ],
 "851": [
  249,
  121,
  255
 ],
 "852": [
  255,
  179,
  231
 ],
 "853": [
  79,
  194,
  68
 ],
 "854": [
  27,
  123,
  104
 ],
 "855": [
  198,
  198,
  198
 ],
 "856": [
  255,
  144,
  159
 ],
 "857": [
  19,
  167,
  119
 ],
 "858": [
  204,
  197,
  198
 ],
 "859": [
  255,
  175,
  210
 ],
 "860": [
  255,
  181,
  93
 ],
 "861": [
  79,
  194,
  68
 ],
 "862": [
  24,
  129,
  94
 ],
 "863": [
  206,
  206,
  206
 ],
 "864": [
  255,
  128,
  132
 ],
 "865": [
  26,
  127,
  102
 ],
 "866": [
  207,
  203,
  203
 ],
 "867": [
  251,
  137,
  102
 ],
 "868": [
  254,
  204,
  119
 ],
 "869": [
  14,
  140,
  140
 ],
 "870": [
  75,
  181,
  71
 ],
 "871": [
  201,
  200,
  200
 ],
 "872": [
  254,
  163,
  248
 ],
 "873": [
  22,
  125,
  92
 ],
 "874": [
  248,
  123,
  253
 ],
 "875": [
  253,
  207,
  109
 ],
 "876": [
  206,
  204,
  203
 ],
 "877": [
  199,
  198,
  198
 ],
 "878": [
  19,
  123,
  95
 ],
 "879": [
  29,
  175,
  160
 ],
 "880": [
  252,
  148,
  125
 ],
 "881": [
  249,
  173,
  102
 ],
 "882": [
  33,
  155,
  98
 ],
 "883": [
  255,
  164,
  121
 ],
 "884": [
  206,
  206,
  206
 ],
 "885": [
  203,
  203,
  203
 ],
 "886": [
  30,
  171,
  106
 ],
 "887": [
  253,
  177,
  219
 ],
 "888": [
  0,
  0,
  0
 ],
 "889": [
  21,
  122,
  101
 ],
 "890": [
  255,
  176,
  96
 ],
 "891": [
  250,
  136,
  103
 ],
 "892": [
  196,
  196,
  196
 ],
 "893": [
  26,
  134,
  58
 ],
 "894": [
  23,
  168,
  125
 ],
 "895": [
  13,
  159,
  145
 ],
 "896": [
  200,
  200,
  200
 ],
 "897": [
  13,
  185,
  155
 ],
 "898": [
  255,
  202,
  133
 ],
 "899": [
  255,
  152,
  109
 ],
 "900": [
  195,
  195,
  195
 ],
 "901": [
  206,
  206,
  206
 ],
 "902": [
  2,
  141,
  145
 ],
 "903": [
  255,
  157,
  175
 ],
 "904": [
  144,
  164,
  200
 ],
 "905": [
  7,
  143,
  142
 ],
 "906": [
  27,
  168,
  156
 ],
 "907": [
  253,
  134,
  134
 ],
 "908": [
  214,
  200,
  204
 ],
 "909": [
  50,
  184,
  37
 ],
 "910": [
  39,
  132,
  108
 ],
 "911": [
  201,
  201,
  201
 ],
 "912": [
  255,
  237,
  139
 ],
 "913": [
  6,
  109,
  137
 ],
 "914": [
  249,
  65,
  103
 ],
 "915": [
  253,
  176,
  95
 ],
 "916": [
  211,
  211,
  211
 ],
 "917": [
  201,
  201,
  201
 ],
 "918": [
  47,
  184,
  37
 ],
 "919": [
  63,
  159,
  111
 ],
 "920": [
  233,
  244,
  137
 ],
 "921": [
  28,
  122,
  109
 ],
 "922": [
  0,
  0,
  0
 ],
 "923": [
  251,
  155,
  122
 ],
 "924": [
  206,
  206,
  206
 ],
 "925": [
  210,
  202,
  203
 ],
 "926": [
  57,
  183,
  44
 ],
 "927": [
  66,
  168,
  102
 ],
 "928": [
  252,
  238,
  149
 ],
 "929": [
  22,
  132,
  102
 ],
 "930": [
  255,
  139,
  145
 ],
 "931": [
  255,
  156,
  129
 ],
 "932": [
  207,
  207,
  207
 ],
 "933": [
  201,
  194,
  192
 ],
 "934": [
  55,
  178,
  34
 ],
 "935": [
  60,
  166,
  118
 ],
 "936": [
  238,
  254,
  135
 ],
 "937": [
  10,
  104,
  141
 ],
 "938": [
  253,
  175,
  214
 ],
 "939": [
  244,
  172,
  222
 ],
 "940": [
  205,
  205,
  205
 ],
 "941": [
  202,
  201,
  201
 ],
 "942": [
  160,
  238,
  157
 ],
 "943": [
  29,
  158,
  87
 ],
 "944": [
  248,
  255,
  137
 ],
 "945": [
  29,
  126,
  86
 ],
 "946": [
  255,
  72,
  61
 ],
 "947": [
  31,
  150,
  82
 ],
 "948": [
  205,
  205,
  205
 ],
 "949": [
  212,
  208,
  209
 ],
 "950": [
  26,
  132,
  99
 ],
 "951": [
  251,
  247,
  140
 ],
 "952": [
  157,
  238,
  149
 ],
 "953": [
  246,
  132,
  152
 ],
 "954": [
  0,
  156,
  139
 ],
 "955": [
  255,
  173,
  222
 ],
 "956": [
  215,
  215,
  215
 ],
 "957": [
  242,
  254,
  135
 ],
 "958": [
  251,
  145,
  155
 ],
 "959": [
  0,
  102,
  150
 ],
 "960": [
  201,
  196,
  196
 ],
 "961": [
  106,
  203,
  186
 ],
 "962": [
  27,
  153,
  86
 ],
 "963": [
  251,
  170,
  221
 ],
 "964": [
  193,
  188,
  189
 ],
 "965": [
  23,
  167,
  167
 ],
 "966": [
  160,
  236,
  147
 ],
 "967": [
  206,
  206,
  206
 ],
 "968": [
  255,
  234,
  128
 ],
 "969": [
  31,
  141,
  86
 ],
 "970": [
  255,
  177,
  213
 ],
 "971": [
  200,
  191,
  192
 ],
 "972": [
  47,
  168,
  80
 ],
 "973": [
  4,
  108,
  138
 ],
 "974": [
  23,
  126,
  78
 ],
 "975": [
  250,
  134,
  252
 ],
 "976": [
  254,
  255,
  144
 ],
 "977": [
  8,
  156,
  146
 ],
 "978": [
  255,
  176,
  212
 ],
 "979": [
  207,
  200,
  200
 ],
 "980": [
  255,
  64,
  69
 ],
 "981": [
  30,
  128,
  95
 ],
 "982": [
  118,
  213,
  68
 ],
 "983": [
  200,
  199,
  199
 ],
 "984": [
  252,
  239,
  142
 ],
 "985": [
  29,
  153,
  99
 ],
 "986": [
  208,
  204,
  203
 ],
 "987": [
  255,
  186,
  134
 ],
 "988": [
  14,
  155,
  158
 ],
 "989": [
  255,
  253,
  190
 ],
 "990": [
  0,
  151,
  105
 ],
 "991": [
  204,
  204,
  204
 ],
 "992": [
  229,
  255,
  135
 ],
 "993": [
  31,
  154,
  85
 ],
 "994": [
  192,
  192,
  192
 ],
 "995": [
  255,
  188,
  221
 ],
 "996": [
  32,
  148,
  95
 ],
 "998": [
  123,
  177,
  239
 ],
 "999": [
  39,
  182,
  49
 ],
 "1000": [
  198,
  198,
  198
 ],
 "1001": [
  255,
  254,
  149
 ],
 "1002": [
  0,
  150,
  143
 ],
 "1003": [
  210,
  206,
  206
 ],
 "1004": [
  248,
  66,
  58
 ],
 "1005": [
  1,
  110,
  148
 ],
 "1006": [
  22,
  127,
  112
 ],
 "1007": [
  255,
  222,
  145
 ],
 "1008": [
  251,
  128,
  156
 ],
 "1009": [
  204,
  204,
  204
 ],
 "1010": [
  11,
  171,
  139
 ],
 "1011": [
  0,
  160,
  159
 ],
 "1012": [
  206,
  206,
  206
 ],
 "1014": [
  255,
  150,
  166
 ],
 "1015": [
  65,
  164,
  96
 ],
 "1016": [
  210,
  207,
  205
 ],
 "1017": [
  249,
  230,
  147
 ],
 "1018": [
  0,
  154,
  130
 ],
 "1019": [
  206,
  203,
  202
 ],
 "1020": [
  255,
  135,
  162
 ],
 "1021": [
  33,
  160,
  90
 ],
 "1022": [
  129,
  142,
  198
 ],
 "1023": [
  1,
  109,
  150
 ],
 "1024": [
  170,
  170,
  170
 ],
 "1025": [
  245,
  255,
  149
 ],
 "1026": [
  22,
  134,
  96
 ],
 "1027": [
  1,
  108,
  143
 ],
 "1028": [
  204,
  203,
  203
 ],
 "1029": [
  255,
  141,
  157
 ],
 "1030": [
  25,
  121,
  108
 ],
 "1031": [
  126,
  143,
  208
 ],
 "1032": [
  180,
  177,
  178
 ],
 "1033": [
  246,
  247,
  141
 ],
 "1034": [
  102,
  203,
  147
 ],
 "1035": [
  22,
  127,
  86
 ],
 "1036": [
  203,
  203,
  203
 ],
 "1037": [
  72,
  200,
  60
 ],
 "1038": [
  22,
  116,
  81
 ],
 "1039": [
  254,
  160,
  213
 ],
 "1040": [
  171,
  171,
  171
 ],
 "1041": [
  253,
  240,
  147
 ],
 "1042": [
  99,
  202,
  164
 ],
 "1043": [
  213,
  213,
  213
 ],
 "1044": [
  251,
  131,
  147
 ],
 "1045": [
  10,
  156,
  113
 ],
 "1046": [
  7,
  134,
  138
 ],
 "1047": [
  20,
  127,
  108
 ],
 "1048": [
  252,
  187,
  217
 ],
 "1049": [
  253,
  251,
  138
 ],
 "1050": [
  99,
  207,
  149
 ],
 "1051": [
  206,
  205,
  205
 ],
 "1052": [
  250,
  159,
  239
 ],
 "1053": [
  68,
  164,
  103
 ],
 "1054": [
  93,
  180,
  110
 ],
 "1055": [
  171,
  171,
  171
 ],
 "1056": [
  255,
  247,
  147
 ],
 "1057": [
  0,
  156,
  117
 ],
 "1058": [
  19,
  165,
  154
 ],
 "1059": [
  98,
  207,
  149
 ],
 "1060": [
  201,
  201,
  201
 ],
 "1061": [
  255,
  132,
  240
 ],
 "1062": [
  22,
  121,
  107
 ],
 "1063": [
  171,
  171,
  171
 ],
 "1064": [
  230,
  253,
  150
 ],
 "1065": [
  255,
  155,
  136
 ],
 "1066": [
  5,
  131,
  135
 ],
 "1067": [
  98,
  200,
  147
 ],
 "1068": [
  203,
  201,
  200
 ],
 "1069": [
  251,
  161,
  188
 ],
 "1070": [
  21,
  120,
  128
 ],
 "1071": [
  170,
  170,
  170
 ],
 "1072": [
  255,
  125,
  133
 ],
 "1073": [
  255,
  252,
  145
 ],
 "1074": [
  11,
  103,
  145
 ],
 "1075": [
  105,
  212,
  173
 ],
 "1076": [
  206,
  205,
  205
 ],
 "1077": [
  248,
  135,
  145
 ],
 "1078": [
  170,
  161,
  161
 ],
 "1079": [
  248,
  149,
  130
 ],
 "1080": [
  126,
  208,
  75
 ],
 "1081": [
  94,
  185,
  106
 ],
 "1082": [
  90,
  198,
  138
 ],
 "1083": [
  202,
  202,
  202
 ],
 "1084": [
  89,
  185,
  71
 ],
 "1085": [
  35,
  158,
  84
 ],
 "1086": [
  24,
  122,
  111
 ],
 "1087": [
  177,
  167,
  169
 ],
 "1088": [
  253,
  117,
  120
 ],
 "1089": [
  126,
  208,
  75
 ],
 "1090": [
  23,
  128,
  83
 ],
 "1091": [
  255,
  253,
  137
 ],
 "1092": [
  201,
  198,
  198
 ],
 "1093": [
  254,
  182,
  125
 ],
 "1094": [
  23,
  126,
  83
 ],
 "1095": [
  171,
  171,
  171
 ],
 "1096": [
  255,
  155,
  143
 ],
 "1097": [
  230,
  68,
  56
 ],
 "1098": [
  252,
  180,
  201
 ],
 "1099": [
  203,
  195,
  195
 ],
 "1100": [
  233,
  146,
  255
 ],
 "1101": [
  34,
  156,
  110
 ],
 "1102": [
  19,
  130,
  118
 ],
 "1103": [
  160,
  160,
  160
 ],
 "1104": [
  253,
  138,
  135
 ],
 "1105": [
  116,
  158,
  214
 ],
 "1106": [
  19,
  172,
  159
 ],
 "1107": [
  254,
  188,
  224
 ],
 "1108": [
  207,
  207,
  207
 ],
 "1109": [
  249,
  95,
  65
 ],
 "1110": [
  255,
  114,
  59
 ],
 "1111": [
  25,
  126,
  97
 ],
 "1112": [
  166,
  166,
  166
 ],
 "1113": [
  255,
  138,
  156
 ],
 "1114": [
  14,
  129,
  142
 ],
 "1116": [
  193,
  193,
  193
 ],
 "1117": [
  255,
  195,
  149
 ],
 "1118": [
  253,
  49,
  85
 ],
 "1119": [
  178,
  174,
  174
 ],
 "1120": [
  250,
  140,
  137
 ],
 "1121": [
  29,
  185,
  29
 ],
 "1123": [
  201,
  201,
  201
 ],
 "1124": [
  255,
  71,
  71
 ],
 "1125": [
  36,
  141,
  115
 ],
 "1126": [
  255,
  64,
  65
 ],
 "1127": [
  15,
  176,
  176
 ],
 "1128": [
  25,
  127,
  112
 ],
 "1129": [
  255,
  112,
  128
 ],
 "1131": [
  202,
  202,
  202
 ],
 "1132": [
  255,
  174,
  111
 ],
 "1133": [
  41,
  184,
  36
 ],
 "1139": [
  153,
  233,
  216
 ],
 "1140": [
  146,
  229,
  193
 ],
 "1141": [
  170,
  233,
  198
 ],
 "1142": [
  156,
  229,
  215
 ],
 "1143": [
  236,
  231,
  84
 ],
 "1144": [
  255,
  252,
  145
 ],
 "1145": [
  255,
  252,
  145
 ],
 "10671": [
  242,
  72,
  59
 ],
 "10672": [
  236,
  231,
  84
 ],
 "10673": [
  255,
  252,
  145
 ],
 "10674": [
  255,
  252,
  145
 ],
 "10675": [
  236,
  231,
  84
 ],
 "10676": [
  255,
  252,
  145
 ],
 "10677": [
  255,
  252,
  145
 ],
 "10678": [
  236,
  231,
  84
 ],
 "10679": [
  255,
  252,
  145
 ],
 "10680": [
  255,
  252,
  145
 ],
 "10681": [
  236,
  231,
  84
 ],
 "10682": [
  255,
  252,
  145
 ],
 "10683": [
  255,
  252,
  145
 ],
 "10684": [
  236,
  231,
  84
 ],
 "10685": [
  255,
  252,
  145
 ],
 "10686": [
  255,
  252,
  145
 ],
 "10687": [
  236,
  231,
  84
 ],
 "10688": [
  255,
  252,
  145
 ],
 "10689": [
  255,
  252,
  145
 ],
 "10690": [
  236,
  231,
  84
 ],
 "10691": [
  255,
  252,
  145
 ],
 "10692": [
  255,
  252,
  145
 ],
 "10693": [
  116,
  212,
  104
 ],
 "10694": [
  103,
  212,
  101
 ],
 "10695": [
  140,
  222,
  117
 ],
 "10696": [
  58,
  199,
  59
 ],
 "10697": [
  92,
  198,
  62
 ],
 "10698": [
  59,
  198,
  51
 ],
 "10699": [
  88,
  189,
  65
 ],
 "10700": [
  110,
  192,
  77
 ],
 "10701": [
  85,
  181,
  69
 ],
 "10702": [
  126,
  208,
  75
 ],
 "10703": [
  126,
  208,
  75
 ],
 "10704": [
  126,
  208,
  75
 ],
 "10705": [
  236,
  231,
  84
 ],
 "10706": [
  255,
  252,
  145
 ],
 "10707": [
  255,
  252,
  145
 ],
 "10708": [
  236,
  231,
  84
 ],
 "10709": [
  255,
  252,
  145
 ],
 "10710": [
  255,
  252,
  145
 ],
 "10711": [
  236,
  231,
  84
 ],
 "10712": [
  255,
  252,
  145
 ],
 "10713": [
  255,
  252,
  145
 ],
 "10714": [
  236,
  231,
  84
 ],
 "10715": [
  255,
  252,
  145
 ],
 "10716": [
  255,
  252,
  145
 ],
 "10717": [
  236,
  231,
  84
 ],
 "10718": [
  255,
  252,
  145
 ],
 "10719": [
  255,
  252,
  145
 ],
 "10720": [
  236,
  231,
  84
 ],
 "10721": [
  255,
  252,
  145
 ],
 "10722": [
  255,
  252,
  145
 ],
 "10723": [
  236,
  231,
  84
 ],
 "10724": [
  255,
  252,
  145
 ],
 "10725": [
  255,
  252,
  145
 ],
 "10726": [
  236,
  231,
  84
 ],
 "10727": [
  255,
  252,
  145
 ],
 "10728": [
  255,
  252,
  145
 ],
 "10729": [
  236,
  231,
  84
 ],
 "10730": [
  255,
  252,
  145
 ],
 "10731": [
  255,
  252,
  145
 ],
 "10732": [
  236,
  231,
  84
 ],
 "10733": [
  255,
  252,
  145
 ],
 "10734": [
  255,
  252,
  145
 ],
 "10735": [
  236,
  231,
  84
 ],
 "10736": [
  255,
  252,
  145
 ],
 "10737": [
  255,
  252,
  145
 ],
 "12993": [
  24,
  128,
  109
 ],
 "12994": [
  22,
  127,
  81
 ],
 "12995": [
  23,
  123,
  104
 ],
 "12996": [
  16,
  123,
  95
 ],
 "12997": [
  27,
  129,
  89
 ],
 "12998": [
  20,
  134,
  101
 ],
 "182305689": [
  22,
  134,
  82
 ],
 "182305693": [
  21,
  119,
  88
 ],
 "182305697": [
  24,
  126,
  89
 ],
 "182305701": [
  25,
  127,
  93
 ],
 "182305705": [
  24,
  124,
  122
 ],
 "182305709": [
  30,
  121,
  104
 ],
 "182305713": [
  22,
  120,
  125
 ],
 "304325711": [
  127,
  46,
  126
 ],
 "312782546": [
  0,
  173,
  177
 ],
 "312782550": [
  3,
  110,
  173
 ],
 "312782554": [
  5,
  172,
  175
 ],
 "312782558": [
  0,
  169,
  166
 ],
 "312782562": [
  6,
  166,
  151
 ],
 "312782566": [
  3,
  98,
  164
 ],
 "312782570": [
  4,
  145,
  178
 ],
 "312782574": [
  9,
  142,
  142
 ],
 "312782578": [
  8,
  144,
  115
 ],
 "312782582": [
  6,
  135,
  143
 ],
 "312782586": [
  3,
  141,
  130
 ],
 "312782590": [
  15,
  134,
  126
 ],
 "312782594": [
  9,
  113,
  145
 ],
 "312782598": [
  6,
  118,
  133
 ],
 "312782604": [
  0,
  144,
  161
 ],
 "312782608": [
  0,
  167,
  142
 ],
 "312782612": [
  0,
  144,
  170
 ],
 "312782616": [
  4,
  153,
  163
 ],
 "312782620": [
  2,
  159,
  172
 ],
 "312782624": [
  1,
  163,
  171
 ],
 "312782628": [
  9,
  143,
  124
 ],
 "312782632": [
  6,
  140,
  143
 ],
 "312782636": [
  9,
  133,
  143
 ],
 "312782640": [
  6,
  126,
  132
 ],
 "312782644": [
  13,
  141,
  112
 ],
 "312782648": [
  7,
  130,
  137
 ],
 "312782652": [
  7,
  105,
  146
 ],
 "480149202": [
  30,
  125,
  100
 ],
 "480149206": [
  17,
  117,
  108
 ],
 "480149210": [
  28,
  135,
  110
 ],
 "480149214": [
  23,
  135,
  110
 ],
 "480149218": [
  18,
  126,
  91
 ],
 "480149222": [
  24,
  130,
  122
 ],
 "480149226": [
  23,
  137,
  115
 ],
 "480149230": [
  1,
  148,
  128
 ],
 "480149234": [
  2,
  138,
  152
 ],
 "480149238": [
  0,
  117,
  141
 ],
 "480149242": [
  0,
  153,
  154
 ],
 "480149246": [
  12,
  129,
  155
 ],
 "480149250": [
  0,
  145,
  150
 ],
 "480149254": [
  0,
  148,
  157
 ],
 "480149258": [
  29,
  171,
  135
 ],
 "480149262": [
  24,
  163,
  140
 ],
 "480149266": [
  27,
  151,
  160
 ],
 "480149270": [
  21,
  157,
  157
 ],
 "480149274": [
  25,
  140,
  154
 ],
 "480149278": [
  23,
  162,
  146
 ],
 "480149282": [
  24,
  162,
  145
 ],
 "480149286": [
  29,
  167,
  147
 ],
 "480149290": [
  26,
  168,
  117
 ],
 "480149294": [
  23,
  162,
  167
 ],
 "480149298": [
  25,
  145,
  161
 ],
 "480149302": [
  32,
  138,
  163
 ],
 "480149306": [
  25,
  153,
  164
 ],
 "480149310": [
  22,
  163,
  128
 ],
 "480149314": [
  15,
  161,
  118
 ],
 "480149318": [
  23,
  161,
  176
 ],
 "480149322": [
  25,
  143,
  162
 ],
 "480149326": [
  27,
  167,
  126
 ],
 "480149330": [
  29,
  149,
  162
 ],
 "480149334": [
  22,
  162,
  147
 ],
 "480149338": [
  19,
  172,
  165
 ],
 "484682470": [
  88,
  186,
  72
 ],
 "484682475": [
  96,
  185,
  69
 ],
 "484682479": [
  88,
  186,
  72
 ],
 "484682483": [
  86,
  184,
  75
 ],
 "484682487": [
  88,
  186,
  72
 ],
 "484682492": [
  88,
  184,
  77
 ],
 "484682496": [
  88,
  186,
  72
 ],
 "484682500": [
  86,
  184,
  75
 ],
 "484682504": [
  88,
  186,
  72
 ],
 "484682508": [
  51,
  185,
  50
 ],
 "484682512": [
  202,
  194,
  194
 ],
 "484682516": [
  202,
  202,
  202
 ],
 "484682520": [
  199,
  199,
  199
 ],
 "484682524": [
  210,
  210,
  210
 ],
 "484682528": [
  199,
  199,
  199
 ],
 "496345664": [
  253,
  119,
  142
 ],
 "496345668": [
  255,
  139,
  158
 ],
 "496345672": [
  252,
  122,
  130
 ],
 "526157192": [
  36,
  149,
  86
 ],
 "526157196": [
  40,
  138,
  64
 ],
 "526322264": [
  36,
  134,
  73
 ],
 "527696977": [
  34,
  129,
  107
 ],
 "549009199": [
  125,
  210,
  243
 ],
 "549009203": [
  245,
  133,
  251
 ],
 "549009207": [
  247,
  133,
  233
 ],
 "549009211": [
  250,
  144,
  255
 ],
 "549009215": [
  255,
  187,
  132
 ],
 "549009219": [
  255,
  164,
  134
 ],
 "549009223": [
  253,
  206,
  135
 ],
 "549009227": [
  248,
  185,
  131
 ],
 "560581551": [
  251,
  160,
  161
 ],
 "560581555": [
  248,
  136,
  163
 ],
 "560581559": [
  253,
  138,
  164
 ],
 "560581563": [
  255,
  151,
  176
 ],
 "563807435": [
  255,
  146,
  129
 ],
 "563807439": [
  255,
  141,
  156
 ],
 "576073699": [
  252,
  122,
  62
 ],
 "576073704": [
  241,
  112,
  70
 ],
 "589508447": [
  51,
  185,
  50
 ],
 "589508451": [
  255,
  161,
  199
 ],
 "589508455": [
  255,
  251,
  174
 ],
 "599626923": [
  233,
  123,
  254
 ],
 "599626927": [
  255,
  186,
  125
 ],
 "606826647": [
  253,
  63,
  57
 ],
 "606826651": [
  251,
  80,
  52
 ],
 "606826655": [
  252,
  65,
  69
 ],
 "606826659": [
  248,
  99,
  54
 ],
 "606826663": [
  255,
  149,
  252
 ],
 "607344830": [
  255,
  144,
  236
 ],
 "607344834": [
  255,
  173,
  251
 ],
 "607344838": [
  253,
  161,
  249
 ],
 "607344842": [
  245,
  156,
  251
 ],
 "607344846": [
  255,
  170,
  250
 ],
 "607344850": [
  252,
  162,
  251
 ],
 "607344854": [
  255,
  165,
  253
 ],
 "607344858": [
  245,
  173,
  255
 ],
 "607344862": [
  233,
  155,
  245
 ],
 "614454277": [
  236,
  143,
  252
 ]
}